mealy.v
//iverilog -o .\file_name.vvp .\module_tb.v
//vvp file_name.vvp
//gtkwave.exe .\module.vcd
module seq_detector_0110_mealy(x,clk,z,reset);
    input x,clk,reset;
    output reg z;
    reg [1:0] ps,ns;
    parameter s0=0, s1=1, s2=2, s3=3;
    always @(posedge clk or posedge reset) 
        if(reset) ps<=s0;
        else ps<=ns;
    always @(ps,x)
    begin
        z=0;
        case (ps)
            s0: begin
                ns=x?s0:s1;
            end 
            s1: begin
                ns=x?s2:s1;
            end
            s2: begin
                ns=x?s3:s1;
            end
            s3: begin
                z=x?0:1;
                ns=x?s0:s1;
            end
            default: begin
                ns=s0;
                z=0;
            end
        endcase
    end
endmodule

moore.v
module seq_detector_0110_moore (
    input clk,
    input reset,
    input x,
    output reg z
);
    reg [2:0] ps, ns;
    parameter S0 = 3'b000,  // Start
              S1 = 3'b001,  // Got 0
              S2 = 3'b010,  // Got 01
              S3 = 3'b011,  // Got 011
              S4 = 3'b100;  // Got 0110 (final)

    always @(posedge clk or posedge reset) begin
        if (reset)    ps <= S0;
        else    ps <= ns;
    end

    always @(*) begin
        case (ps)
            S0: ns = (x == 0) ? S1 : S0;
            S1: ns = (x == 1) ? S2 : S1;
            S2: ns = (x == 1) ? S3 : S1;
            S3: ns = (x == 0) ? S4 : S0;
            S4: ns = (x == 0) ? S1 : S2;  
            default: ns = S0;
        endcase
    end

    always @(*) begin
        case (ps)
            S4: z = 1;  
            default: z = 0;
        endcase
    end

endmodule

sequence_detector_tb.v
`timescale 1ns/1ns
`include "mealy.v"
`include "moore.v"
module module_tb;
    reg x,clk,reset;
    wire z;
    seq_detector_0110_moore DUT(.x(x), .clk(clk), .reset(reset), .z(z));
    initial begin
        clk=0; reset=1; x=0;
    end

    initial begin
        #7 reset=0;
        #10 x=0;
        #10 x=1;
        #10 x=0;
        #10 x=1;
        #10 x=1;
        #10 reset=1;x=0;
        #1 reset=0;
        #9 x=1;
        #10 x=1;
        #10 x=0;
        #10 x=0;
        #30 $finish;
    end
    always #5 clk=~clk;
    initial begin
        $dumpfile("module.vcd");
        $dumpvars(0,module_tb);
        $monitor($time, " reset=%b, x=%b, z=%b",reset,x,z);
    end
endmodule

module.vcd
$date
	Thu Jul 31 16:11:21 2025
$end
$version
	Icarus Verilog
$end
$timescale
	1ns
$end
$scope module module_tb $end
$var wire 1 ! z $end
$var reg 1 " clk $end
$var reg 1 # reset $end
$var reg 1 $ x $end
$scope module DUT $end
$var wire 1 " clk $end
$var wire 1 # reset $end
$var wire 1 $ x $end
$var parameter 3 % S0 $end
$var parameter 3 & S1 $end
$var parameter 3 ' S2 $end
$var parameter 3 ( S3 $end
$var parameter 3 ) S4 $end
$var reg 3 * ns [2:0] $end
$var reg 3 + ps [2:0] $end
$var reg 1 ! z $end
$upscope $end
$upscope $end
$enddefinitions $end
$comment Show the parameter values. $end
$dumpall
b100 )
b11 (
b10 '
b1 &
b0 %
$end
#0
$dumpvars
b0 +
b1 *
0$
1#
0"
0!
$end
#5
1"
#7
0#
#10
0"
#15
b1 +
1"
#20
0"
#25
1"
#27
b10 *
1$
#30
0"
#35
b11 *
b10 +
1"
#37
b1 *
0$
#40
0"
#45
b1 +
1"
#47
b10 *
1$
#50
0"
#55
b11 *
b10 +
1"
#60
0"
#65
b0 *
b11 +
1"
#67
b0 +
b1 *
0$
1#
#68
0#
#70
0"
#75
b1 +
1"
#77
b10 *
1$
#80
0"
#85
b11 *
b10 +
1"
#90
0"
#95
b0 *
b11 +
1"
#97
b100 *
0$
#100
0"
#105
1!
b1 *
b100 +
1"
#110
0"
#115
0!
b1 +
1"
